odoo/addons/account_reconcile_rule/README.rst
odoo/addons/account_reconcile_rule/__init__.py
odoo/addons/account_reconcile_rule/__manifest__.py
odoo/addons/account_reconcile_rule/i18n/account_reconcile_rule.pot
odoo/addons/account_reconcile_rule/i18n/am.po
odoo/addons/account_reconcile_rule/i18n/ca.po
odoo/addons/account_reconcile_rule/i18n/de.po
odoo/addons/account_reconcile_rule/i18n/el_GR.po
odoo/addons/account_reconcile_rule/i18n/es.po
odoo/addons/account_reconcile_rule/i18n/es_ES.po
odoo/addons/account_reconcile_rule/i18n/fi.po
odoo/addons/account_reconcile_rule/i18n/fr.po
odoo/addons/account_reconcile_rule/i18n/gl.po
odoo/addons/account_reconcile_rule/i18n/hr_HR.po
odoo/addons/account_reconcile_rule/i18n/it.po
odoo/addons/account_reconcile_rule/i18n/pt.po
odoo/addons/account_reconcile_rule/i18n/pt_BR.po
odoo/addons/account_reconcile_rule/i18n/pt_PT.po
odoo/addons/account_reconcile_rule/i18n/sl.po
odoo/addons/account_reconcile_rule/i18n/tr.po
odoo/addons/account_reconcile_rule/models/__init__.py
odoo/addons/account_reconcile_rule/models/account_journal.py
odoo/addons/account_reconcile_rule/models/account_reconcile_rule.py
odoo/addons/account_reconcile_rule/models/account_statement_line.py
odoo/addons/account_reconcile_rule/security/ir.model.access.csv
odoo/addons/account_reconcile_rule/static/description/icon.png
odoo/addons/account_reconcile_rule/static/src/js/account_widgets.js
odoo/addons/account_reconcile_rule/tests/__init__.py
odoo/addons/account_reconcile_rule/tests/common.py
odoo/addons/account_reconcile_rule/tests/test_journal.py
odoo/addons/account_reconcile_rule/tests/test_rule_currency.py
odoo/addons/account_reconcile_rule/tests/test_rule_rounding.py
odoo/addons/account_reconcile_rule/views/account_reconcile_rule.xml
odoo/addons/account_reconcile_rule/views/account_reconcile_rule_view.xml
odoo11_addon_account_reconcile_rule-11.0.1.0.0.99.dev3.dist-info/METADATA
odoo11_addon_account_reconcile_rule-11.0.1.0.0.99.dev3.dist-info/WHEEL
odoo11_addon_account_reconcile_rule-11.0.1.0.0.99.dev3.dist-info/top_level.txt
odoo11_addon_account_reconcile_rule-11.0.1.0.0.99.dev3.dist-info/RECORD
